setup.py
fixedrobo/__init__.py
fixedrobo/browser.py
fixedrobo/cache.py
fixedrobo/compat.py
fixedrobo/exceptions.py
fixedrobo/helpers.py
fixedrobo/ordereddict.py
fixedrobo/responses.py
fixedrobo.egg-info/PKG-INFO
fixedrobo.egg-info/SOURCES.txt
fixedrobo.egg-info/dependency_links.txt
fixedrobo.egg-info/requires.txt
fixedrobo.egg-info/top_level.txt
fixedrobo/forms/__init__.py
fixedrobo/forms/fields.py
fixedrobo/forms/form.py