Metadata-Version: 1.2
Name: fixedrobo
Version: 1.2
Summary: Fixed version of robobrowser
Home-page: UNKNOWN
Author: noidea
Author-email: 
License: UNKNOWN
Platform: UNKNOWN
Classifier: Programming Language :: Python :: 3
Classifier: License :: OSI Approved :: BSD License
Classifier: Operating System :: OS Independent
Requires-Python: >=3.6
